faceverify/__init__.py
faceverify/__main__.py
faceverify/cli.py
faceverify/cli/__init__.py
faceverify/config/__init__.py
faceverify/config/defaults.py
faceverify/config/settings.py
faceverify/core/__init__.py
faceverify/core/pipeline.py
faceverify/core/result.py
faceverify/core/verifier.py
faceverify/decision/__init__.py
faceverify/decision/adaptive.py
faceverify/decision/base.py
faceverify/decision/threshold.py
faceverify/detection/__init__.py
faceverify/detection/base.py
faceverify/detection/factory.py
faceverify/detection/mediapipe.py
faceverify/detection/mtcnn.py
faceverify/detection/opencv.py
faceverify/detection/retinaface.py
faceverify/embedding/__init__.py
faceverify/embedding/arcface.py
faceverify/embedding/base.py
faceverify/embedding/facenet.py
faceverify/embedding/factory.py
faceverify/embedding/vggface.py
faceverify/exceptions/__init__.py
faceverify/exceptions/errors.py
faceverify/preprocessing/__init__.py
faceverify/preprocessing/alignment.py
faceverify/preprocessing/normalization.py
faceverify/similarity/__init__.py
faceverify/similarity/engine.py
faceverify/similarity/metrics.py
faceverify/utils/__init__.py
faceverify/utils/gpu.py
faceverify/utils/image.py
faceverify/utils/model_loader.py
faceverify/utils/validators.py
faceverify_sdk-1.0.0rc1.dist-info/licenses/LICENSE
faceverify_sdk-1.0.0rc1.dist-info/METADATA
faceverify_sdk-1.0.0rc1.dist-info/WHEEL
faceverify_sdk-1.0.0rc1.dist-info/entry_points.txt
faceverify_sdk-1.0.0rc1.dist-info/top_level.txt
faceverify_sdk-1.0.0rc1.dist-info/RECORD
