Metadata-Version: 2.4
Name: faceverify-sdk
Version: 1.0.0rc1
Summary: A modular, open-source face verification SDK for Python
Home-page: https://github.com/nayandas69/faceverify
Author: nayandas69
Author-email: nayandas69 <nayanchandradas@hotmail.com>
Maintainer-email: nayandas69 <nayanchandradas@hotmail.com>
License: MIT
Project-URL: Homepage, https://github.com/nayandas69/faceverify
Project-URL: Documentation, https://github.com/nayandas69/faceverify#readme
Project-URL: Repository, https://github.com/nayandas69/faceverify
Project-URL: Changelog, https://github.com/nayandas69/faceverify/blob/main/CHANGELOG.md
Project-URL: Bug Tracker, https://github.com/nayandas69/faceverify/issues
Keywords: face-recognition,face-verification,face-detection,deep-learning,computer-vision,biometrics,identity-verification,facenet,deepface,opencv
Classifier: Development Status :: 5 - Production/Stable
Classifier: Intended Audience :: Developers
Classifier: Intended Audience :: Science/Research
Classifier: License :: OSI Approved :: MIT License
Classifier: Operating System :: OS Independent
Classifier: Programming Language :: Python :: 3
Classifier: Programming Language :: Python :: 3.8
Classifier: Programming Language :: Python :: 3.9
Classifier: Programming Language :: Python :: 3.10
Classifier: Programming Language :: Python :: 3.11
Classifier: Programming Language :: Python :: 3.12
Classifier: Topic :: Scientific/Engineering :: Artificial Intelligence
Classifier: Topic :: Scientific/Engineering :: Image Recognition
Classifier: Topic :: Software Development :: Libraries :: Python Modules
Requires-Python: >=3.8
License-File: LICENSE
Requires-Dist: numpy>=1.21.0
Requires-Dist: opencv-python>=4.5.0
Requires-Dist: Pillow>=8.0.0
Requires-Dist: scikit-learn>=1.0.0
Requires-Dist: deepface>=0.0.79
Requires-Dist: tf-keras>=2.15.0
Requires-Dist: pyyaml>=6.0
Requires-Dist: pydantic>=2.0.0
Requires-Dist: tqdm>=4.64.0
Requires-Dist: structlog>=23.0.0
Provides-Extra: dev
Requires-Dist: pytest>=7.0.0; extra == "dev"
Requires-Dist: pytest-cov>=4.0.0; extra == "dev"
Requires-Dist: pytest-asyncio>=0.21.0; extra == "dev"
Requires-Dist: black>=23.0.0; extra == "dev"
Requires-Dist: isort>=5.12.0; extra == "dev"
Requires-Dist: flake8>=6.0.0; extra == "dev"
Requires-Dist: mypy>=1.0.0; extra == "dev"
Requires-Dist: pre-commit>=3.0.0; extra == "dev"
Provides-Extra: docs
Requires-Dist: sphinx>=6.0.0; extra == "docs"
Requires-Dist: sphinx-rtd-theme>=1.2.0; extra == "docs"
Requires-Dist: myst-parser>=1.0.0; extra == "docs"
Provides-Extra: gpu
Requires-Dist: tensorflow>=2.10.0; extra == "gpu"
Requires-Dist: onnxruntime-gpu>=1.12.0; extra == "gpu"
Provides-Extra: api
Requires-Dist: fastapi>=0.100.0; extra == "api"
Requires-Dist: uvicorn>=0.22.0; extra == "api"
Requires-Dist: python-multipart>=0.0.6; extra == "api"
Provides-Extra: detection
Requires-Dist: mtcnn>=0.1.1; extra == "detection"
Requires-Dist: mediapipe>=0.10.0; extra == "detection"
Provides-Extra: all
Requires-Dist: faceverify-sdk[api,detection,dev,docs]; extra == "all"
Dynamic: author
Dynamic: home-page
Dynamic: license-file
Dynamic: requires-python
